{"width":20,"height":25,"players":[{"username":"ali","password":"ali","nickname":"Ali"},{"username":"aryan","password":"1234","nickname":"Aryan"}],"seed":123456789,"allActions":[{"username":"ali","cityUserAction":{"x1":5,"y1":0,"x2":3,"y2":1,"actionType":"BUY_TILE"}},{"username":"ali","cityUserAction":{"x1":5,"y1":0,"x2":0,"y2":0,"actionType":"BUY_UNIT","unitType":"WORKER"}},{"username":"ali","unitUserAction":{"x1":5,"y1":0,"x2":3,"y2":1,"isMilitary":false,"actionType":"MOVE"}},{"username":"ali","unitUserAction":{"x1":3,"y1":1,"x2":0,"y2":0,"isMilitary":false,"actionType":"DELETE"}},{"username":"ali","cityUserAction":{"x1":5,"y1":0,"x2":0,"y2":0,"actionType":"BUY_UNIT","unitType":"WARRIOR"}},{"username":"ali","unitUserAction":{"x1":5,"y1":0,"x2":6,"y2":2,"isMilitary":true,"actionType":"MOVE"}},{"username":"ali","cityUserAction":{"x1":5,"y1":0,"x2":6,"y2":2,"actionType":"BUY_TILE"}},{"username":"ali","cityUserAction":{"x1":5,"y1":0,"x2":0,"y2":0,"actionType":"BUY_UNIT","unitType":"SCOUT"}}]}